LAB01_B1021136.v
// module should without number 
module HalfAdder (carry,sum,a,b);

    input a,b;
    output sum,carry;

    xor M1(sum,a,b);
    and M2(carry,a,b);
    
endmodule

module FullAdder(sum,c_out,a,b,c_in);
    input a,b,c_in;
    output sum,c_out;
    wire w1,w2,w3;

    HalfAdder M1(w2,w1,a,b);
    HalfAdder M2(w3,sum,c_in,w1);
           or M3(c_out,w2,w3);
endmodule

module sixteen_adder_subtractor(oflow,c_out, sum, a, b, m);

        input [15:0] a,b ; 
        input m;
    
        output oflow,c_out;
        output  [15:0] sum;
        wire [15:1] c;
        wire [15:0] x;
        assign x[15:0] = b[15:0] ^ m;
        /*
        xor xor0(x[0],b[0],m);
        xor xor1(x[1],b[1],m);
        xor xor2(x[2],b[2],m);
        xor xor3(x[3],b[3],m);
        xor xor4(x[4],b[4],m);
        xor xor5(x[5],b[5],m);
        xor xor6(x[6],b[6],m);
        xor xor7(x[7],b[7],m);
        xor xor8(x[8],b[8],m);
        xor xor9(x[9],b[9],m);
        xor xor10(x[10],b[10],m);
        xor xor11(x[11],b[11],m);
        xor xor12(x[12],b[12],m);
        xor xor13(x[13],b[13],m);
        xor xor14(x[14],b[14],m);
        xor xor15(x[15],b[15],m);
        */
        FullAdder FA1(sum[0],c[1],a[0],x[0],m);
        FullAdder FA2(sum[1],c[2],a[1],x[1],c[1]);
        FullAdder FA3(sum[2],c[3],a[2],x[2],c[2]);
        FullAdder FA4(sum[3],c[4],a[3],x[3],c[3]);
        FullAdder FA5(sum[4],c[5],a[4],x[4],c[4]);
        FullAdder FA6(sum[5],c[6],a[5],x[5],c[4]);
        FullAdder FA7(sum[6],c[7],a[6],x[6],c[5]);
        FullAdder FA8(sum[7],c[8],a[7],x[7],c[6]);
        FullAdder FA9(sum[8],c[9],a[8],x[8],c[7]);
        FullAdder FA10(sum[9],c[10],a[9],x[9],c[8]);
        FullAdder FA11(sum[10],c[11],a[10],x[10],c[9]);
        FullAdder FA12(sum[11],c[12],a[11],x[11],c[10]);
        FullAdder FA13(sum[12],c[13],a[12],x[11],c[11]);
        FullAdder FA14(sum[13],c[14],a[13],x[13],c[12]);
        FullAdder FA15(sum[14],c[15],a[14],x[14],c[13]);
        FullAdder FA16(sum[15],c_out,a[15],x[15],c[14]);
        xor of(oflow,c_out,c[15]);

endmodule    

`timescale 1 ns/1 ns
module adder_tb();
    reg clk;
    reg [15:0]a,i;
    reg m;
    wire [15:0]s;
    wire oflow,c_out;
    integer k,test_num=100;

    `define ADD 0
    `define SUB 1
    initial m= `SUB; // m=`SUB 減法
    `define period 10
    
   sixteen_adder_subtractor as1(.oflow(oflow),.sum(s),.c_out(c_out),.a(a),.b(i),.m(m));
        // .模組內名稱(tb內名稱)
    initial clk = 0;
    always #(`period/2) clk= ~clk;
    initial begin
        a=0 ; i=0;
        for (k=0;k<test_num;k=k+1) begin
            @(posedge clk)
            a = $random ;i=$random;
            operation_display;
        end
        $finish;    
    end

    task operation_display;
        begin
            $display("m=%b ,a=%d, i=%d ,s=%d ,c_out =%b, oflow=%b ", m,a,i,s,c_out,oflow);
        end    
    endtask
    //加入波型
    initial begin

    $dumpfile("addsub.vcd");
    $dumpvars;
    end
    
endmodule

addsub.vcd
$date
	Tue Oct 25 21:14:30 2022
$end
$version
	Icarus Verilog
$end
$timescale
	1ns
$end
$scope module adder_tb $end
$var wire 16 ! s [15:0] $end
$var wire 1 " oflow $end
$var wire 1 # c_out $end
$var reg 16 $ a [15:0] $end
$var reg 1 % clk $end
$var reg 16 & i [15:0] $end
$var reg 1 ' m $end
$var integer 32 ( k [31:0] $end
$var integer 32 ) test_num [31:0] $end
$scope module as1 $end
$var wire 16 * a [15:0] $end
$var wire 16 + b [15:0] $end
$var wire 1 ' m $end
$var wire 1 " oflow $end
$var wire 16 , x [15:0] $end
$var wire 16 - sum [15:0] $end
$var wire 1 # c_out $end
$var wire 15 . c [15:1] $end
$scope module FA1 $end
$var wire 1 / a $end
$var wire 1 0 b $end
$var wire 1 ' c_in $end
$var wire 1 1 c_out $end
$var wire 1 2 w3 $end
$var wire 1 3 w2 $end
$var wire 1 4 w1 $end
$var wire 1 5 sum $end
$scope module M1 $end
$var wire 1 / a $end
$var wire 1 0 b $end
$var wire 1 3 carry $end
$var wire 1 4 sum $end
$upscope $end
$scope module M2 $end
$var wire 1 ' a $end
$var wire 1 4 b $end
$var wire 1 2 carry $end
$var wire 1 5 sum $end
$upscope $end
$upscope $end
$scope module FA10 $end
$var wire 1 6 a $end
$var wire 1 7 b $end
$var wire 1 8 c_in $end
$var wire 1 9 c_out $end
$var wire 1 : w3 $end
$var wire 1 ; w2 $end
$var wire 1 < w1 $end
$var wire 1 = sum $end
$scope module M1 $end
$var wire 1 6 a $end
$var wire 1 7 b $end
$var wire 1 ; carry $end
$var wire 1 < sum $end
$upscope $end
$scope module M2 $end
$var wire 1 8 a $end
$var wire 1 < b $end
$var wire 1 : carry $end
$var wire 1 = sum $end
$upscope $end
$upscope $end
$scope module FA11 $end
$var wire 1 > a $end
$var wire 1 ? b $end
$var wire 1 @ c_in $end
$var wire 1 A c_out $end
$var wire 1 B w3 $end
$var wire 1 C w2 $end
$var wire 1 D w1 $end
$var wire 1 E sum $end
$scope module M1 $end
$var wire 1 > a $end
$var wire 1 ? b $end
$var wire 1 C carry $end
$var wire 1 D sum $end
$upscope $end
$scope module M2 $end
$var wire 1 @ a $end
$var wire 1 D b $end
$var wire 1 B carry $end
$var wire 1 E sum $end
$upscope $end
$upscope $end
$scope module FA12 $end
$var wire 1 F a $end
$var wire 1 G b $end
$var wire 1 H c_in $end
$var wire 1 I c_out $end
$var wire 1 J w3 $end
$var wire 1 K w2 $end
$var wire 1 L w1 $end
$var wire 1 M sum $end
$scope module M1 $end
$var wire 1 F a $end
$var wire 1 G b $end
$var wire 1 K carry $end
$var wire 1 L sum $end
$upscope $end
$scope module M2 $end
$var wire 1 H a $end
$var wire 1 L b $end
$var wire 1 J carry $end
$var wire 1 M sum $end
$upscope $end
$upscope $end
$scope module FA13 $end
$var wire 1 N a $end
$var wire 1 O b $end
$var wire 1 P c_in $end
$var wire 1 Q c_out $end
$var wire 1 R w3 $end
$var wire 1 S w2 $end
$var wire 1 T w1 $end
$var wire 1 U sum $end
$scope module M1 $end
$var wire 1 N a $end
$var wire 1 O b $end
$var wire 1 S carry $end
$var wire 1 T sum $end
$upscope $end
$scope module M2 $end
$var wire 1 P a $end
$var wire 1 T b $end
$var wire 1 R carry $end
$var wire 1 U sum $end
$upscope $end
$upscope $end
$scope module FA14 $end
$var wire 1 V a $end
$var wire 1 W b $end
$var wire 1 X c_in $end
$var wire 1 Y c_out $end
$var wire 1 Z w3 $end
$var wire 1 [ w2 $end
$var wire 1 \ w1 $end
$var wire 1 ] sum $end
$scope module M1 $end
$var wire 1 V a $end
$var wire 1 W b $end
$var wire 1 [ carry $end
$var wire 1 \ sum $end
$upscope $end
$scope module M2 $end
$var wire 1 X a $end
$var wire 1 \ b $end
$var wire 1 Z carry $end
$var wire 1 ] sum $end
$upscope $end
$upscope $end
$scope module FA15 $end
$var wire 1 ^ a $end
$var wire 1 _ b $end
$var wire 1 ` c_in $end
$var wire 1 a c_out $end
$var wire 1 b w3 $end
$var wire 1 c w2 $end
$var wire 1 d w1 $end
$var wire 1 e sum $end
$scope module M1 $end
$var wire 1 ^ a $end
$var wire 1 _ b $end
$var wire 1 c carry $end
$var wire 1 d sum $end
$upscope $end
$scope module M2 $end
$var wire 1 ` a $end
$var wire 1 d b $end
$var wire 1 b carry $end
$var wire 1 e sum $end
$upscope $end
$upscope $end
$scope module FA16 $end
$var wire 1 f a $end
$var wire 1 g b $end
$var wire 1 h c_in $end
$var wire 1 # c_out $end
$var wire 1 i w3 $end
$var wire 1 j w2 $end
$var wire 1 k w1 $end
$var wire 1 l sum $end
$scope module M1 $end
$var wire 1 f a $end
$var wire 1 g b $end
$var wire 1 j carry $end
$var wire 1 k sum $end
$upscope $end
$scope module M2 $end
$var wire 1 h a $end
$var wire 1 k b $end
$var wire 1 i carry $end
$var wire 1 l sum $end
$upscope $end
$upscope $end
$scope module FA2 $end
$var wire 1 m a $end
$var wire 1 n b $end
$var wire 1 o c_in $end
$var wire 1 p c_out $end
$var wire 1 q w3 $end
$var wire 1 r w2 $end
$var wire 1 s w1 $end
$var wire 1 t sum $end
$scope module M1 $end
$var wire 1 m a $end
$var wire 1 n b $end
$var wire 1 r carry $end
$var wire 1 s sum $end
$upscope $end
$scope module M2 $end
$var wire 1 o a $end
$var wire 1 s b $end
$var wire 1 q carry $end
$var wire 1 t sum $end
$upscope $end
$upscope $end
$scope module FA3 $end
$var wire 1 u a $end
$var wire 1 v b $end
$var wire 1 w c_in $end
$var wire 1 x c_out $end
$var wire 1 y w3 $end
$var wire 1 z w2 $end
$var wire 1 { w1 $end
$var wire 1 | sum $end
$scope module M1 $end
$var wire 1 u a $end
$var wire 1 v b $end
$var wire 1 z carry $end
$var wire 1 { sum $end
$upscope $end
$scope module M2 $end
$var wire 1 w a $end
$var wire 1 { b $end
$var wire 1 y carry $end
$var wire 1 | sum $end
$upscope $end
$upscope $end
$scope module FA4 $end
$var wire 1 } a $end
$var wire 1 ~ b $end
$var wire 1 !" c_in $end
$var wire 1 "" c_out $end
$var wire 1 #" w3 $end
$var wire 1 $" w2 $end
$var wire 1 %" w1 $end
$var wire 1 &" sum $end
$scope module M1 $end
$var wire 1 } a $end
$var wire 1 ~ b $end
$var wire 1 $" carry $end
$var wire 1 %" sum $end
$upscope $end
$scope module M2 $end
$var wire 1 !" a $end
$var wire 1 %" b $end
$var wire 1 #" carry $end
$var wire 1 &" sum $end
$upscope $end
$upscope $end
$scope module FA5 $end
$var wire 1 '" a $end
$var wire 1 (" b $end
$var wire 1 )" c_in $end
$var wire 1 *" c_out $end
$var wire 1 +" w3 $end
$var wire 1 ," w2 $end
$var wire 1 -" w1 $end
$var wire 1 ." sum $end
$scope module M1 $end
$var wire 1 '" a $end
$var wire 1 (" b $end
$var wire 1 ," carry $end
$var wire 1 -" sum $end
$upscope $end
$scope module M2 $end
$var wire 1 )" a $end
$var wire 1 -" b $end
$var wire 1 +" carry $end
$var wire 1 ." sum $end
$upscope $end
$upscope $end
$scope module FA6 $end
$var wire 1 /" a $end
$var wire 1 0" b $end
$var wire 1 1" c_in $end
$var wire 1 2" c_out $end
$var wire 1 3" w3 $end
$var wire 1 4" w2 $end
$var wire 1 5" w1 $end
$var wire 1 6" sum $end
$scope module M1 $end
$var wire 1 /" a $end
$var wire 1 0" b $end
$var wire 1 4" carry $end
$var wire 1 5" sum $end
$upscope $end
$scope module M2 $end
$var wire 1 1" a $end
$var wire 1 5" b $end
$var wire 1 3" carry $end
$var wire 1 6" sum $end
$upscope $end
$upscope $end
$scope module FA7 $end
$var wire 1 7" a $end
$var wire 1 8" b $end
$var wire 1 9" c_in $end
$var wire 1 :" c_out $end
$var wire 1 ;" w3 $end
$var wire 1 <" w2 $end
$var wire 1 =" w1 $end
$var wire 1 >" sum $end
$scope module M1 $end
$var wire 1 7" a $end
$var wire 1 8" b $end
$var wire 1 <" carry $end
$var wire 1 =" sum $end
$upscope $end
$scope module M2 $end
$var wire 1 9" a $end
$var wire 1 =" b $end
$var wire 1 ;" carry $end
$var wire 1 >" sum $end
$upscope $end
$upscope $end
$scope module FA8 $end
$var wire 1 ?" a $end
$var wire 1 @" b $end
$var wire 1 A" c_in $end
$var wire 1 B" c_out $end
$var wire 1 C" w3 $end
$var wire 1 D" w2 $end
$var wire 1 E" w1 $end
$var wire 1 F" sum $end
$scope module M1 $end
$var wire 1 ?" a $end
$var wire 1 @" b $end
$var wire 1 D" carry $end
$var wire 1 E" sum $end
$upscope $end
$scope module M2 $end
$var wire 1 A" a $end
$var wire 1 E" b $end
$var wire 1 C" carry $end
$var wire 1 F" sum $end
$upscope $end
$upscope $end
$scope module FA9 $end
$var wire 1 G" a $end
$var wire 1 H" b $end
$var wire 1 I" c_in $end
$var wire 1 J" c_out $end
$var wire 1 K" w3 $end
$var wire 1 L" w2 $end
$var wire 1 M" w1 $end
$var wire 1 N" sum $end
$scope module M1 $end
$var wire 1 G" a $end
$var wire 1 H" b $end
$var wire 1 L" carry $end
$var wire 1 M" sum $end
$upscope $end
$scope module M2 $end
$var wire 1 I" a $end
$var wire 1 M" b $end
$var wire 1 K" carry $end
$var wire 1 N" sum $end
$upscope $end
$upscope $end
$upscope $end
$scope task operation_display $end
$upscope $end
$upscope $end
$enddefinitions $end
#0
$dumpvars
0N"
0M"
0L"
0K"
0J"
0I"
0H"
0G"
0F"
0E"
0D"
0C"
0B"
0A"
0@"
0?"
0>"
0="
0<"
0;"
0:"
09"
08"
07"
06"
05"
04"
03"
02"
01"
00"
0/"
0."
0-"
0,"
0+"
0*"
0)"
0("
0'"
0&"
0%"
0$"
0#"
0""
0!"
0~
0}
0|
0{
0z
0y
0x
0w
0v
0u
1t
0s
0r
0q
0p
1o
0n
0m
0l
0k
0j
0i
0h
0g
0f
0e
0d
0c
0b
0a
0`
0_
0^
0]
0\
0[
0Z
0Y
0X
0W
0V
0U
0T
0S
0R
0Q
0P
0O
0N
0M
0L
0K
0J
0I
0H
0G
0F
0E
0D
0C
0B
0A
0@
0?
0>
0=
0<
0;
0:
09
08
07
06
05
14
03
12
11
10
0/
b1 .
b10 -
b1 ,
b0 +
b0 *
b1100100 )
b0 (
1'
b0 &
0%
b0 $
0#
0"
b10 !
$end
#5
1"
0t
1a
0o
1b
01
1P
1`
15
02
1F"
1=
1A
1M
b101010000000000 .
1Q
0e
04
1E"
1<
1C
1L
1S
1d
1|
16"
1N"
0E
1U
b11101110100101 !
b11101110100101 -
1]
00
1@"
17
1?
1G
1O
1_
1{
15"
1M"
0D
0T
1\
b101111010000000 ,
1u
1/"
1G"
1>
1N
1V
b1 (
b101111010000001 &
b101111010000001 +
b11010100100100 $
b11010100100100 *
1%
#10
0%
#15
1w
1p
1q
1`
1o
0t
1>"
0F"
0U
1R
1Q
11
1H
1s
1="
0E"
0L
1T
0S
05
12
1|
1&"
16"
0N"
0=
b101011000000011 .
19
0]
1e
0b
b1100100001101100 !
b1100100001101100 -
1l
1n
10"
18"
0@"
0G
0O
14
0{
1%"
15"
0M"
0<
1;
0\
0d
1c
1k
b101011001100010 ,
1/
0u
1}
0/"
0G"
16
0V
1^
1f
b10 (
b101011001100011 &
b101011001100011 +
b1101011000001001 $
b1101011000001001 *
1%
#20
0%
#25
1#
1i
1h
1Y
0w
1."
0"
1Z
0p
11"
1)"
1@
0H
1!"
1X
1t
0q
1&"
1""
16"
0>"
1F"
1J"
1=
09
0R
0e
1b
1a
1x
0P
1I
0s
1z
0%"
1$"
05"
0="
1E"
1L"
1<
0;
1K
0T
1S
1d
0c
0|
0y
0N"
1E
b111100100001101 .
0A
0M
0J
0]
b11010111010 !
b11010111010 -
0l
0n
1v
1~
00"
08"
1@"
1H"
07
0?
1G
1O
0_
1g
0{
0M"
0D
0C
0L
1\
1k
b1001100110001100 ,
1u
1G"
0>
1F
1V
0f
b11 (
b1001100110001101 &
b1001100110001101 +
b111101100001101 $
b111101100001101 *
1%
#30
0%
#35
0I"
0:"
0;"
09"
1y
0*"
1w
1."
0+"
1p
1!"
0A"
0P
0h
0"
15
02
0t
1q
0|
1x
0F"
01"
0)"
02"
0@
0A
0X
0`
0Y
0a
0#
04
13
1s
1{
0z
1-"
0E"
1&"
0#"
0""
16"
03"
1>"
0N"
0J"
1=
1E
0B
0M
0I
0U
b111 .
0Q
0]
0Z
1e
0b
b1100011001111001 !
b1100011001111001 -
1l
0i
10
1n
0v
0~
1("
0@"
0H"
17
0G
0O
1_
0g
0%"
0$"
15"
1="
0M"
0L"
1<
1D
0L
0K
0T
0S
0\
1d
1k
0j
b101001000010011 ,
0}
1/"
17"
0G"
06
1>
0F
0N
0V
0^
1f
b100 (
b101001000010010 &
b101001000010010 +
b1000010001100101 $
b1000010001100101 *
1%
#40
0%
#45
1`
1Q
1R
0h
1P
0Y
1A
0Z
0w
01"
0)"
1B
1M
0X
1o
0p
0""
1@
0I
0!"
05
12
11
1t
0q
1&"
0#"
0."
1J"
0J
0U
0l
1#
0x
0H
14
03
0s
1%"
0-"
1L"
1L
1T
0k
1j
1|
0y
06"
0>"
0N"
1=
09
0E
1]
b110101000001110 !
b110101000001110 -
1e
b101010100000001 .
1a
00
0n
1v
1~
0("
1H"
07
1?
1G
1O
1g
1{
05"
0="
0M"
1<
0;
1D
1\
0d
1c
b1100110100001100 ,
0u
0/"
07"
1G"
16
0>
1V
1^
b101 (
b1100110100001101 &
b1100110100001101 +
b1110001100000001 $
b1110001100000001 *
1%
#50
0%
#55
1N"
1I"
1:"
11"
1)"
1;"
1F"
1""
19"
1A"
0o
0w
0&"
1#"
1*"
12"
01
0p
1!"
1,"
14"
15
02
1t
0q
0|
b101010101111100 .
1x
1."
16"
0>"
0=
b111100110110011 !
b111100110110011 -
1U
0R
1("
10"
04
1s
0{
1z
0-"
05"
1="
0<
0T
1S
b1100110100111100 ,
0/
1m
1u
1'"
1/"
17"
06
1N
b110 (
b1100110100111101 &
b1100110100111101 +
b1111000101110110 $
b1111000101110110 *
1%
#60
0%
#65
0N"
0I"
1e
0:"
1A"
1H
1`
1o
1>"
0;"
18
06"
13"
12"
19
1M
0U
1R
1Q
11
09"
1B"
1"
13
15"
04"
1D"
1;
0L
1T
0S
15
02
1t
1&"
0#"
1."
0+"
b101011110101101 .
0*"
1F"
0C"
1=
1E
0B
1]
b1110111011011011 !
b1110111011011011 -
1l
0#
10
0("
00"
1@"
17
0G
0O
1W
04
0s
0%"
1$"
0-"
0,"
0E"
0<
0D
1C
1\
1k
0j
b1111011110001101 ,
1/
0m
1}
0'"
1?"
16
1>
0V
0f
b111 (
b1111011110001100 &
b1111011110001100 +
b101011111101101 $
b101011111101101 *
1%
#70
0%
#75
0&"
1#"
1F"
1A"
1y
12"
1w
06"
13"
1K"
1p
11"
1)"
1I"
1@
19"
0X
0`
0t
1q
1""
1>"
1:"
0N"
1J"
1e
0b
0a
1i
1!"
1*"
0H
1P
0I
0Q
1h
1"
1s
1%"
0$"
0="
1<"
1M"
0L"
1d
0c
0|
1x
0."
1+"
1=
0:
09
0E
1B
1A
1M
0J
1U
0R
0]
b10010111111111 .
1Y
b101101011000001 !
b101101011000001 -
0l
1#
1n
0~
18"
0H"
07
0_
0g
1{
0z
1-"
0<
0;
1D
0C
1L
0T
0\
1[
1k
0j
b10010011000111 ,
0u
1'"
06
0>
1F
0N
1V
1f
b1000 (
b10010011000110 &
b10010011000110 +
b1110100111111001 $
b1110100111111001 *
1%
#80
0%
#85
1H
1F"
0U
0I"
19
1!"
11"
1)"
09"
1A"
0@
0P
1>"
0;"
0:"
0=
1:
0i
1x
1""
0*"
12"
0J"
0A
0h
1="
0<"
1<
0k
1j
0|
1y
0&"
1#"
1."
0+"
06"
13"
0N"
0K"
1E
0B
1M
0]
b1010101111 .
0Y
b100110011010001 !
b100110011010001 -
1e
0v
1~
10"
08"
17
0?
0W
1_
1g
1{
0z
1%"
0-"
15"
0M"
1D
0C
0L
0\
0[
1d
b1101001010101011 ,
1u
0}
0'"
0/"
0G"
1>
0F
0V
0^
b1001 (
b1101001010101010 &
b1101001010101010 +
b1000010011000101 $
b1000010011000101 *
1%
#90
0%
#95
1`
1Q
1R
1P
1A
0E
1B
1w
1@
0"
1p
1J"
0t
1q
01"
0)"
09"
1K"
1i
1o
0""
0*"
1I"
18
1h
05
12
11
1|
0y
1&"
0#"
1."
0+"
0>"
1:"
0F"
1C"
1B"
1Y
0l
1#
14
03
0{
1z
0%"
1-"
0="
1<"
1E"
0D"
1[
1k
0j
06"
03"
0N"
1=
0:
0U
0]
b100101000011100 !
b100101000011100 -
1e
b111011111100111 .
1a
00
1v
0~
1("
18"
0@"
1W
0g
05"
14"
1M"
0<
1;
1T
0\
0d
1c
b111001001110110 ,
1/"
1G"
16
1N
1V
1^
b1010 (
b111001001110111 &
b111001001110111 +
b1111011111100101 $
b1111011111100101 *
1%
#100
0%
#105
1+"
11"
1)"
0P
1""
0A
1X
0&"
1#"
0=
1E
0B
1I
0o
08
0@
0M
1J
0U
0R
0i
01
1!"
19"
0A"
0I"
0B"
0J"
0h
1%"
1L
0T
1S
0k
1j
15
02
0t
0q
0|
1y
1x
0."
1*"
16"
02"
1>"
0:"
1F"
0C"
1N"
0K"
b110010111100001 !
b110010111100001 -
1]
b101101000011110 .
0Y
1~
0("
00"
08"
1@"
1H"
1G
1O
0W
1g
04
0s
1r
1{
0z
1-"
0,"
05"
04"
0="
0<"
1E"
1M"
0\
0[
b1101101110001110 ,
0/
1m
0u
1'"
0/"
07"
0?"
0G"
0V
b1011 (
b1101101110001111 &
b1101101110001111 +
b1101011000010010 $
b1101011000010010 *
1%
#110
0%
#115
1t
1o
1P
1K"
1i
11
1A
1A"
1I"
1:
1X
1h
05
12
1B
0a
12"
1:"
18
1@
1H
1I
0`
1Y
1"
14
1<"
1d
0c
06"
13"
1>"
0;"
1F"
1B"
0N"
1J"
0=
19
0E
0M
1J
1U
b10111111111111 .
0Q
0]
1Z
b101000011000010 !
b101000011000010 -
0l
1#
10
18"
0H"
1?
0G
0O
0_
15"
0="
0E"
1D"
1M"
0L"
1<
0;
1D
1L
0K
0T
0S
1\
1k
0j
b1001011011001111 ,
1/"
17"
1?"
1G"
06
0>
1F
0N
1V
0f
b1100 (
b1001011011001110 &
b1001011011001110 +
b110100111110010 $
b110100111110010 *
1%
#120
0%
#125
0F"
0A"
0P
0!"
02"
0A
0o
0x
16"
03"
0>"
1E
0B
01
0#
1|
0y
01"
0)"
09"
0@
1`
15
02
1M
0J
1e
1a
1l
0i
0w
0""
0*"
0J"
1Q
04
0L
1K
1S
0d
1c
0k
0t
0q
b111101011000000 .
0p
1&"
0#"
0."
0+"
1N"
0K"
1=
0:
b1100111100101101 !
b1100111100101101 -
0U
0R
00
0n
0~
1G
1O
1_
0g
0s
0r
1%"
0$"
0-"
0M"
0<
1;
0T
b100111011000100 ,
0m
1}
0'"
0G"
16
1N
b1101 (
b100111011000101 &
b100111011000101 +
b111101011101000 $
b111101011101000 *
1%
#130
0%
#135
1C"
1A"
12"
13"
1;"
0"
1l
11"
1)"
19"
1I"
1@
0M
1h
1""
1*"
0>"
1:"
1E
0a
1!"
18
1J"
0H
0`
1Y
0%"
1$"
1,"
1="
0<"
0D
1d
0c
0|
1x
1."
06"
0F"
1B"
0N"
1K"
1=
0:
09
1U
b10100111111100 .
0Q
b1101011000011001 !
b1101011000011001 -
0]
1Z
1~
1("
10"
08"
07
0?
1W
0_
0{
1z
0-"
15"
1E"
0D"
1M"
0<
0;
1T
0S
1\
b10100010111100 ,
1u
1'"
0/"
0?"
1G"
06
0N
0V
b1110 (
b10100010111101 &
b10100010111101 +
b100100101011100 $
b100100101011100 *
1%
#140
0%
#145
0l
0h
0"
0J
0R
0Y
08
0H
0P
1]
0Z
1t
0a
11"
1)"
0B"
09
0A
0X
1o
0I"
0@
1e
0b
0&"
1#"
1""
1F"
0C"
1=
0:
1E
0B
1M
0I
11
09"
0:"
0J"
0`
1%"
0$"
0E"
1<
1D
1L
0K
05
12
1."
0+"
0*"
16"
03"
1>"
0;"
0N"
0K"
b111111011110010 !
b111111011110010 -
1U
b101101 .
0Q
0~
0("
18"
0@"
17
1?
0G
0O
14
0-"
0,"
05"
14"
1="
0M"
1T
0S
b10011001100100 ,
1/
0'"
1/"
07"
0G"
1N
b1111 (
b10011001100101 &
b10011001100101 +
b101100000101101 $
b101100000101101 *
1%
#150
0%
#155
0P
0A
1E
0B
0F"
1N"
0@
1l
0"
0."
0A"
0J"
0#
1w
01"
0)"
15
02
16"
03"
02"
0K"
0i
1p
0!"
0""
0I"
1H
0h
04
13
1r
15"
04"
1M"
1k
1t
0q
1|
0x
1&"
0#"
1>"
0:"
0=
19
1M
0U
b1110110101101111 !
b1110110101101111 -
1]
b1000000011 .
0Y
10
1n
0v
1~
00"
08"
1H"
0W
1g
0s
0{
0z
1%"
1="
0<"
0<
1;
0L
0T
1\
0[
b1000011100001011 ,
1m
0u
0}
17"
16
0F
0N
1V
b10000 (
b1000011100001010 &
b1000011100001010 +
b110001001100011 $
b110001001100011 *
1%
#160
0%
#165
0M
0H
1h
0|
0&"
1=
09
0E
0]
1Y
1l
1o
0w
0%"
1<
0;
0D
0\
1[
0k
05
12
11
1t
0q
b10000000000001 .
0p
16"
0>"
1F"
b1000001110100010 !
b1000001110100010 -
0e
0n
0~
10"
07
0?
1W
0g
14
03
0s
0r
15"
0="
1E"
0d
b10000100100001 ,
0/
0m
0/"
07"
1?"
0^
b10001 (
b10000100100000 &
b10000100100000 +
b10001010000000 $
b10001010000000 *
1%
#170
0%
#175
1>"
19"
1`
0!"
1*"
1Q
0x
0o
13"
1+"
1F"
1R
1"
0y
01
11"
1)"
18
1P
0w
15
02
1|
1""
0."
1B"
1A
1M
0U
1a
0p
1A"
0@
0h
04
1{
1$"
1-"
0E"
1D"
1C
1L
1T
1c
1k
1t
0q
0&"
06"
12"
1N"
0J"
1=
0E
0]
b101010010111000 .
0Y
b1100101111000111 !
b1100101111000111 -
1e
00
1v
1~
1("
00"
1@"
0H"
1?
1G
1O
0W
1_
1g
1s
0%"
15"
04"
1M"
0L"
0<
0D
0\
0[
0d
b1100110010011100 ,
1m
1}
1/"
1G"
06
1>
0V
1^
b10010 (
b1100110010011101 &
b1100110010011101 +
b100010110101010 $
b100010110101010 *
1%
#180
0%
#185
1#
1y
0l
1i
1w
08
0P
1h
0A"
0H
1"
0t
1p
1F"
0C"
0B"
1E
0A
1Y
1!"
01"
0)"
02"
09
1X
0s
1r
1E"
0D"
1D
0C
1[
0|
1x
1&"
0""
0."
0+"
06"
03"
0N"
1=
0:
0M
1I
0U
0R
1]
b110011011001001 !
b110011011001001 -
1e
0b
b11100000010110 .
0a
1n
0v
0~
0@"
0?
1W
0_
1{
0z
0%"
0$"
0-"
1,"
05"
0M"
1<
0L
1K
0T
1S
0\
0d
0c
b1011100000010010 ,
1u
0}
1'"
0/"
0G"
16
1F
1N
1V
0^
b10011 (
b1011100000010011 &
b1011100000010011 +
b11111010010110 $
b11111010010110 *
1%
#190
0%
#195
1N"
1I"
1:"
0>"
1;"
0#
0"
1!"
1l
0i
1q
1x
16"
1+"
0X
0`
0h
0a
1o
0|
1y
11"
1)"
1M
0I
1U
0Q
1]
0Z
0Y
1e
0b
11
1w
1""
19"
1="
1L
0K
1T
0S
1\
0[
1d
05
12
0t
1p
0&"
1#"
0."
b1011111 .
1*"
0F"
1=
b1111111100100000 !
b1111111100100000 -
1E
18"
17
1?
0G
0O
0W
1_
14
1s
0r
1%"
1-"
0,"
0E"
1<
1D
b1101011001010010 ,
1/
0m
1}
0'"
0?"
06
0>
b10100 (
b1101011001010011 &
b1101011001010011 +
b11100000001101 $
b11100000001101 *
1%
#200
0%
#205
19"
1H
1*"
19
1i
0."
1+"
0=
1:
1h
11"
1)"
18
1Y
1""
1B"
1U
1Z
1b
0&"
1#"
1C"
1B
1X
1`
1w
1!"
1A"
1@
0F"
1M
1I
1Q
1p
1x
12"
1J"
1P
0"
1E"
0L
1K
0T
1S
0t
1q
0|
1y
06"
13"
1>"
0;"
0N"
1K"
0E
1A
0]
0e
b111111111111111 .
1a
b1100001000000 !
b1100001000000 -
0l
1#
0n
1v
1@"
0?
1G
1O
1W
0_
0g
1s
0r
1{
15"
0="
1<"
1M"
1D
0C
1\
1d
0c
1k
0j
b10101011010100 ,
1m
0u
1/"
17"
1G"
1>
0V
1^
1f
b10101 (
b10101011010101 &
b10101011010101 +
b1101110101101011 $
b1101110101101011 *
1%
#210
0%
#215
18
1B"
09"
0F"
1C"
0a
0*"
1o
11"
1)"
1A"
0@
0P
1e
0b
0"
1t
0q
1."
0+"
11
1""
12"
0I"
0J"
0A
0`
0#
0s
1r
0-"
05
12
0&"
1#"
06"
13"
0>"
0;"
0:"
0N"
0K"
1=
0:
1E
0B
1U
0R
b10101010101111 .
0Q
b1101111000010010 !
b1101111000010010 -
1l
0i
10
1n
1~
0("
10"
08"
1?
14
1%"
15"
0="
0<"
0M"
0<
1;
1D
1T
0S
0k
b11111010101111 ,
0/
0}
0/"
07"
0G"
16
0>
0N
0f
b10110 (
b11111010101110 &
b11111010101110 +
b100101000000010 $
b100101000000010 *
1%
#220
0%
#225
1@
1J"
08
1K"
0B"
1I"
1F"
0C"
1:"
0A"
1;"
1M
0J
02"
0X
1o
19"
0"
16"
03"
0>"
1E
0I
0U
0e
1a
11
1w
1*"
0H
1#
05"
1="
0D
1L
0K
0T
0d
1c
05
12
0t
1q
1p
1|
0y
1&"
0#"
0."
1+"
0N"
1=
0:
b110000101011111 .
09
0]
0Z
b111010101100 !
b111010101100 -
0l
1i
00
00"
18"
0?
0G
0O
1_
14
03
1s
0r
0{
1z
0%"
1$"
1-"
1M"
1<
0;
0\
1[
1k
b111001011001110 ,
1/
0m
1u
1}
1'"
1G"
06
1V
1f
b10111 (
b111001011001111 &
b111001011001111 +
b1110100100011101 $
b1110100100011101 *
1%
#230
0%
